JVLMotor/MotorCom.py
JVLMotor/README.md
JVLMotor/__init__.py
JVLMotor/Motors/MACMotor.py
JVLMotor/Motors/MISMotor.py
JVLMotor/Motors/Motor.py
JVLMotor/Motors/SMC67Motor.py
JVLMotor/Motors/__init__.py
JVLMotor/Protocols/EtherCATDSPProtocol.py
JVLMotor/Protocols/EtherCATRegistersProtocol.py
JVLMotor/Protocols/EthernetIPProtocol.py
JVLMotor/Protocols/MacTalkProtocol.py
JVLMotor/Protocols/ModBusProtocol.py
JVLMotor/Protocols/ProfinetIOProtocol.py
JVLMotor/Protocols/TemplateProtocol.py
JVLMotor/Protocols/__init__.py
JVLMotor/Protocols/Communications/SerialCommunication.py
JVLMotor/Protocols/Communications/TemplateCommunications.py
JVLMotor/Protocols/Communications/__init__.py
JVLMotor/Protocols/Communications/Drivers/APSController.py
JVLMotor/Protocols/Communications/Drivers/CifXDriver.py
JVLMotor/Protocols/Communications/Drivers/CifXErrors.py
JVLMotor/Protocols/Communications/Drivers/EaPsuController.py
JVLMotor/Protocols/Communications/Drivers/WagoController.py
JVLMotor/Protocols/Communications/Drivers/__init__.py
jvlmotor-0.1.0.dist-info/licenses/LICENSE
jvlmotor-0.1.0.dist-info/METADATA
jvlmotor-0.1.0.dist-info/WHEEL
jvlmotor-0.1.0.dist-info/top_level.txt
jvlmotor-0.1.0.dist-info/RECORD
