Metadata-Version: 2.4
Name: JVLMotor
Version: 0.1.0
Summary: A library for JVL motors communication with different protocols
Author: JVL A/S
Author-email: atv@jvl.dk
Maintainer: JVL A/S
Maintainer-email: Support@jvl.dk
License: MIT
Classifier: Programming Language :: Python :: 3
Classifier: License :: OSI Approved :: MIT License
Classifier: Operating System :: Microsoft :: Windows
Requires-Python: >=3.9.4
License-File: LICENSE
Requires-Dist: ea_psu_controller==1.1.0
Requires-Dist: libscrc==1.8.1
Requires-Dist: pymodbus==3.5.2
Requires-Dist: pyserial==3.5
Requires-Dist: pyuac==0.0.3
Requires-Dist: pywinauto==0.6.8
Dynamic: author
Dynamic: author-email
Dynamic: classifier
Dynamic: description
Dynamic: description-content-type
Dynamic: license
Dynamic: license-file
Dynamic: maintainer
Dynamic: maintainer-email
Dynamic: requires-dist
Dynamic: requires-python
Dynamic: summary
